README.rst
setup.py
cloudify_rest_client/__init__.py
cloudify_rest_client/blueprints.py
cloudify_rest_client/bytes_stream_utils.py
cloudify_rest_client/client.py
cloudify_rest_client/cluster.py
cloudify_rest_client/constants.py
cloudify_rest_client/deployment_modifications.py
cloudify_rest_client/deployment_updates.py
cloudify_rest_client/deployments.py
cloudify_rest_client/evaluate.py
cloudify_rest_client/events.py
cloudify_rest_client/exceptions.py
cloudify_rest_client/executions.py
cloudify_rest_client/ldap.py
cloudify_rest_client/maintenance.py
cloudify_rest_client/manager.py
cloudify_rest_client/node_instances.py
cloudify_rest_client/nodes.py
cloudify_rest_client/plugins.py
cloudify_rest_client/responses.py
cloudify_rest_client/search.py
cloudify_rest_client/secrets.py
cloudify_rest_client/snapshots.py
cloudify_rest_client/tenants.py
cloudify_rest_client/tokens.py
cloudify_rest_client/user_groups.py
cloudify_rest_client/users.py
cloudify_rest_client/utils.py
cloudify_rest_client.egg-info/PKG-INFO
cloudify_rest_client.egg-info/SOURCES.txt
cloudify_rest_client.egg-info/dependency_links.txt
cloudify_rest_client.egg-info/requires.txt
cloudify_rest_client.egg-info/top_level.txt
cloudify_rest_client/aria/__init__.py
cloudify_rest_client/aria/exceptions.py
cloudify_rest_client/aria/executions.py
cloudify_rest_client/aria/logs.py
cloudify_rest_client/aria/node_templates.py
cloudify_rest_client/aria/nodes.py
cloudify_rest_client/aria/plugins.py
cloudify_rest_client/aria/service_templates.py
cloudify_rest_client/aria/services.py
cloudify_rest_client/aria/workflows.py
cloudify_rest_client/aria/wrapper.py
cloudify_rest_client/aria/mapi/__init__.py
cloudify_rest_client/aria/mapi/exceptions.py
cloudify_rest_client/aria/mapi/mapi.py
cloudify_rest_client/aria/mapi/wrappers.py