Metadata-Version: 1.0
Name: cloudify-rest-client
Version: 4.3.1
Summary: Cloudify REST client
Home-page: UNKNOWN
Author: cosmo-admin
Author-email: cosmo-admin@gigaspaces.com
License: LICENSE
Platform: UNKNOWN
